supertonic_mnn/__init__.py
supertonic_mnn/cli.py
supertonic_mnn/engine.py
supertonic_mnn/model.py
supertonic_mnn/text.py
supertonic_mnn/wrapper.py
supertonic_mnn-0.1.3.dist-info/METADATA
supertonic_mnn-0.1.3.dist-info/WHEEL
supertonic_mnn-0.1.3.dist-info/entry_points.txt
supertonic_mnn-0.1.3.dist-info/RECORD
