Metadata-Version: 2.4
Name: supertonic-mnn
Version: 0.1.3
Summary: CLI tool for Supertonic MNN inference
Requires-Python: >=3.9
Requires-Dist: huggingface-hub
Requires-Dist: mnn>=2.0.0
Requires-Dist: numpy
Requires-Dist: requests
Requires-Dist: sounddevice>=0.5.3
Requires-Dist: soundfile
Requires-Dist: tqdm
